audiovisually/__init__.py
audiovisually/evaluate.py
audiovisually/predict.py
audiovisually/preprocess.py
audiovisually/train.py
audiovisually/utils.py
cli/__init__.py
cli/main.py
tests/__init__.py
tests/test_evaluate.py
tests/test_pipeline.py
tests/test_predict.py
tests/test_preprocess.py
tests/test_train.py
tests/test_utils.py
audiovisually-0.1.4.dist-info/METADATA
audiovisually-0.1.4.dist-info/WHEEL
audiovisually-0.1.4.dist-info/top_level.txt
audiovisually-0.1.4.dist-info/RECORD
