Metadata-Version: 2.4
Name: audiovisually
Version: 0.1.4
Summary: A package for audiovisual AI processing
Author: Louie Daans
Author-email: louiedaans@gmail.com
Project-URL: Documentation, https://bredauniversityadsai.github.io/2024-25d-fai2-adsai-group-nlp-3/
Project-URL: Source, https://github.com/BredaUniversityADSAI/2024-25d-fai2-adsai-group-nlp-3/tree/main/audiovisually-pack
Requires-Python: >=3.10
Requires-Dist: numpy
Requires-Dist: pandas
Requires-Dist: moviepy
Requires-Dist: googletrans==4.0.2
Requires-Dist: whisper
Requires-Dist: torch
Requires-Dist: nltk
Requires-Dist: assemblyai
Requires-Dist: python-dotenv
Requires-Dist: transformers
Requires-Dist: tqdm
Dynamic: author
Dynamic: author-email
Dynamic: description
Dynamic: description-content-type
Dynamic: project-url
Dynamic: requires-dist
Dynamic: requires-python
Dynamic: summary
